adverseml/__init__.py
adverseml/partitioners/DummyPartitioner.py
adverseml/partitioners/__init__.py
adverseml/poisoners/KNNPoisoner.py
adverseml/poisoners/__init__.py
poisonlib/__init__.py
poisonlib/partitioners/DummyPartitioner.py
poisonlib/partitioners/__init__.py
poisonlib/poisoners/KNNPoisoner.py
poisonlib/poisoners/__init__.py
adverseml-0.0.1.dist-info/METADATA
adverseml-0.0.1.dist-info/WHEEL
adverseml-0.0.1.dist-info/top_level.txt
adverseml-0.0.1.dist-info/RECORD
